tekdrive/__init__.py
tekdrive/authorizer.py
tekdrive/enums.py
tekdrive/exceptions.py
tekdrive/request_wrapper.py
tekdrive/retry.py
tekdrive/routing.py
tekdrive/session.py
tekdrive/settings.py
tekdrive/status_codes.py
tekdrive/tekdrive.py
tekdrive/models/__init__.py
tekdrive/models/base.py
tekdrive/models/helpers.py
tekdrive/models/paginator.py
tekdrive/models/parser.py
tekdrive/models/permissions.py
tekdrive/models/search.py
tekdrive/models/trashcan.py
tekdrive/models/tree.py
tekdrive/models/usage.py
tekdrive/models/user.py
tekdrive/models/drive/__init__.py
tekdrive/models/drive/artifact.py
tekdrive/models/drive/base.py
tekdrive/models/drive/file.py
tekdrive/models/drive/folder.py
tekdrive/models/drive/member.py
tekdrive/models/drive/plan.py
tekdrive/models/drive/trash.py
tekdrive/models/drive/user.py
tekdrive/utils/__init__.py
tekdrive/utils/casing.py
tekdrive-1.1.0.dist-info/LICENSE
tekdrive-1.1.0.dist-info/METADATA
tekdrive-1.1.0.dist-info/WHEEL
tekdrive-1.1.0.dist-info/top_level.txt
tekdrive-1.1.0.dist-info/RECORD
